{
  "ageGroup": "11-12",
  "stageName": "Pre-O Level Foundation",
  "subjects": [
    { "name": "English", "slug": "english", "displayOrder": 1, "units": [{ "title": "Essay and Argument", "slug": "essay-and-argument", "displayOrder": 1, "lessons": [{ "title": "Structured Essay Writing", "slug": "structured-essay-writing", "difficultyIndicator": "pre-o-level-foundation", "displayOrder": 1, "content": { "storyText": "Sadia improved essays by using clear thesis, evidence, and conclusion structure.", "activityInstructions": "Draft a 3-paragraph essay outline with claim and supporting evidence.", "quizConcept": "Essay organization and argument clarity.", "worksheetExample": "Paragraph planner and transition practice.", "parentTip": "Encourage editing drafts, not one-attempt writing." } }] }] },
    { "name": "Mathematics", "slug": "mathematics", "displayOrder": 2, "units": [{ "title": "Algebra Foundations", "slug": "algebra-foundations", "displayOrder": 1, "lessons": [{ "title": "Solving Simple Equations", "slug": "solving-simple-equations", "difficultyIndicator": "pre-o-level-foundation", "displayOrder": 1, "content": { "storyText": "Farhan treated equations as balance puzzles and solved unknowns step by step.", "activityInstructions": "Solve 6 one-step and two-step equations and explain operations used.", "quizConcept": "Algebraic reasoning and balancing method.", "worksheetExample": "Equation solving with verification step.", "parentTip": "Ask child to check answers by substitution." } }] }] },
    { "name": "Science", "slug": "science", "displayOrder": 3, "units": [{ "title": "Scientific Reasoning", "slug": "scientific-reasoning", "displayOrder": 1, "lessons": [{ "title": "Evidence and Explanation", "slug": "evidence-and-explanation", "difficultyIndicator": "pre-o-level-foundation", "displayOrder": 1, "content": { "storyText": "A class compared claims and evidence quality before accepting conclusions.", "activityInstructions": "Evaluate two scientific claims and decide which has stronger evidence.", "quizConcept": "Claim-evidence-reasoning framework.", "worksheetExample": "CER template with sample data.", "parentTip": "Encourage data-backed explanations." } }] }] },
    { "name": "Geography", "slug": "geography", "displayOrder": 4, "units": [{ "title": "Human-Environment Systems", "slug": "human-environment-systems", "displayOrder": 1, "lessons": [{ "title": "Population and Resources", "slug": "population-and-resources", "difficultyIndicator": "pre-o-level-foundation", "displayOrder": 1, "content": { "storyText": "Students studied how population growth affects water, food, and housing needs.", "activityInstructions": "Interpret a simple population chart and suggest sustainable responses.", "quizConcept": "Data interpretation and planning.", "worksheetExample": "Population-resource analysis questions.", "parentTip": "Discuss local resource issues with practical solutions." } }] }] },
    { "name": "History", "slug": "history", "displayOrder": 5, "units": [{ "title": "Historical Analysis", "slug": "historical-analysis", "displayOrder": 1, "lessons": [{ "title": "Interpreting Historical Sources", "slug": "interpreting-historical-sources", "difficultyIndicator": "pre-o-level-foundation", "displayOrder": 1, "content": { "storyText": "Ayaan compared two historical sources and identified perspective differences.", "activityInstructions": "Analyze source origin, purpose, and reliability for two short texts.", "quizConcept": "Source evaluation and bias awareness.", "worksheetExample": "Source analysis grid.", "parentTip": "Ask who wrote the source and for whom." } }] }] },
    { "name": "Computer & Technology", "slug": "computer-and-technology", "displayOrder": 6, "units": [{ "title": "Digital Literacy", "slug": "digital-literacy", "displayOrder": 1, "lessons": [{ "title": "Safe and Smart AI Use", "slug": "safe-and-smart-ai-use", "difficultyIndicator": "pre-o-level-foundation", "displayOrder": 1, "content": { "storyText": "Learners used AI tools responsibly by verifying facts and protecting privacy.", "activityInstructions": "Evaluate AI outputs and mark reliable vs questionable responses with reasons.", "quizConcept": "Responsible AI usage and verification.", "worksheetExample": "AI response audit checklist.", "parentTip": "Teach students to cross-check with trusted sources." } }] }] },
    { "name": "Self Development", "slug": "self-development", "displayOrder": 7, "units": [{ "title": "Leadership Basics", "slug": "leadership-basics", "displayOrder": 1, "lessons": [{ "title": "Goal-Action-Review", "slug": "goal-action-review", "difficultyIndicator": "pre-o-level-foundation", "displayOrder": 1, "content": { "storyText": "Nadia improved performance by setting goals, acting, and reviewing outcomes weekly.", "activityInstructions": "Create a personal study plan and review after 7 days.", "quizConcept": "Independent planning and reflection.", "worksheetExample": "Goal-action-review workbook page.", "parentTip": "Support consistency through weekly check-ins." } }] }] },
    { "name": "Emotional Intelligence", "slug": "emotional-intelligence", "displayOrder": 8, "units": [{ "title": "Self-Regulation", "slug": "self-regulation", "displayOrder": 1, "lessons": [{ "title": "Stress and Coping Skills", "slug": "stress-and-coping-skills", "difficultyIndicator": "pre-o-level-foundation", "displayOrder": 1, "content": { "storyText": "Students learned to manage exam stress with planning and breathing strategies.", "activityInstructions": "Identify stress triggers and assign one coping strategy for each.", "quizConcept": "Stress management and resilience.", "worksheetExample": "Trigger-coping-action map.", "parentTip": "Normalize stress discussions and promote healthy coping." } }] }] },
    { "name": "Health", "slug": "health", "displayOrder": 9, "units": [{ "title": "Well-Being Foundations", "slug": "well-being-foundations", "displayOrder": 1, "lessons": [{ "title": "Balanced Lifestyle", "slug": "balanced-lifestyle", "difficultyIndicator": "pre-o-level-foundation", "displayOrder": 1, "content": { "storyText": "A consistent routine improved concentration, sleep quality, and mood.", "activityInstructions": "Build a weekly health plan and evaluate adherence.", "quizConcept": "Lifestyle design and outcomes.", "worksheetExample": "Habit tracker with analysis.", "parentTip": "Focus on sustainable habits over perfection." } }] }] },
    { "name": "Financial Literacy", "slug": "financial-literacy", "displayOrder": 10, "units": [{ "title": "Budget and Planning", "slug": "budget-and-planning", "displayOrder": 1, "lessons": [{ "title": "Long-Term Saving Goals", "slug": "long-term-saving-goals", "difficultyIndicator": "pre-o-level-foundation", "displayOrder": 1, "content": { "storyText": "Bilal used monthly budgeting to reach a long-term learning goal purchase.", "activityInstructions": "Create a 3-month savings plan with target and weekly actions.", "quizConcept": "Planning, delayed gratification, and discipline.", "worksheetExample": "Savings timeline sheet.", "parentTip": "Help children track progress visually." } }] }] },
    { "name": "Islamic Studies", "slug": "islamic-studies", "displayOrder": 11, "units": [{ "title": "Character and Responsibility", "slug": "character-and-responsibility", "displayOrder": 1, "lessons": [{ "title": "Accountability in Actions", "slug": "accountability-in-actions", "difficultyIndicator": "pre-o-level-foundation", "displayOrder": 1, "content": { "storyText": "A class leader chose fairness over favoritism and strengthened trust.", "activityInstructions": "Evaluate one leadership dilemma and choose accountable action.", "quizConcept": "Accountability and ethical conduct.", "worksheetExample": "Ethical choice decision tree.", "parentTip": "Reinforce fairness in daily family tasks." } }] }] }
  ]
}
